__init__.py
anime_wallpaper.py
anime_wallpaper-1.0.2.dist-info/LICENSE
anime_wallpaper-1.0.2.dist-info/METADATA
anime_wallpaper-1.0.2.dist-info/WHEEL
anime_wallpaper-1.0.2.dist-info/top_level.txt
anime_wallpaper-1.0.2.dist-info/RECORD
