Metadata-Version: 2.1
Name: anime_wallpaper
Version: 1.0.2
Summary: anime/manga wallpaper generator
Author: Nowkzy
License: LICENSE
License-File: LICENSE
